aocli/__init__.py
aocli/cli.py
aocli/console.py
aocli/constants.py
aocli/data.py
aocli/functional.py
aocli/io.py
aocli/py.typed
aocli/session.py
aocli-0.2.0.dist-info/entry_points.txt
aocli-0.2.0.dist-info/LICENSE
aocli-0.2.0.dist-info/WHEEL
aocli-0.2.0.dist-info/METADATA
aocli-0.2.0.dist-info/RECORD
